YuanmengXiangmuBijiWangzhuanJuejinShicaoXiangmuDianzishu1806Fix1/README.md
YuanmengXiangmuBijiWangzhuanJuejinShicaoXiangmuDianzishu1806Fix1/__init__.py
YuanmengXiangmuBijiWangzhuanJuejinShicaoXiangmuDianzishu1806Fix1/__main__.py
YuanmengXiangmuBijiWangzhuanJuejinShicaoXiangmuDianzishu1806Fix1/file.pdf
YuanmengXiangmuBijiWangzhuanJuejinShicaoXiangmuDianzishu1806Fix1/index.html
yuanmeng_xiangmu_biji_wangzhuan_juejin_shicao_xiangmu_dianzishu_1806_fix1-2025.3.24.1.dist-info/METADATA
yuanmeng_xiangmu_biji_wangzhuan_juejin_shicao_xiangmu_dianzishu_1806_fix1-2025.3.24.1.dist-info/WHEEL
yuanmeng_xiangmu_biji_wangzhuan_juejin_shicao_xiangmu_dianzishu_1806_fix1-2025.3.24.1.dist-info/entry_points.txt
yuanmeng_xiangmu_biji_wangzhuan_juejin_shicao_xiangmu_dianzishu_1806_fix1-2025.3.24.1.dist-info/top_level.txt
yuanmeng_xiangmu_biji_wangzhuan_juejin_shicao_xiangmu_dianzishu_1806_fix1-2025.3.24.1.dist-info/RECORD
